README.rst
setup.py
bin/pfdicom_rev
pfdicom_rev/__init__.py
pfdicom_rev/pfdicom.py
pfdicom_rev/pfdicom_rev.py
pfdicom_rev/pfdicom_rev.v1.py
pfdicom_rev.egg-info/PKG-INFO
pfdicom_rev.egg-info/SOURCES.txt
pfdicom_rev.egg-info/dependency_links.txt
pfdicom_rev.egg-info/not-zip-safe
pfdicom_rev.egg-info/requires.txt
pfdicom_rev.egg-info/top_level.txt