Metadata-Version: 1.0
Name: pfdicom-rev
Version: 2.4.16
Summary: Process DICOM trees and create JSON summares for the ReV viewer.
Home-page: https://github.com/FNNDSC/pfdicom_rev
Author: FNNDSC
Author-email: dev@babymri.org
License: MIT
Platform: UNKNOWN
